textcraft/__init__.py
textcraft/crafting_tree.py
textcraft/env.py
textcraft/utils.py
textcraft/data/recipes/acacia_boat.json
textcraft/data/recipes/acacia_button.json
textcraft/data/recipes/acacia_door.json
textcraft/data/recipes/acacia_fence.json
textcraft/data/recipes/acacia_fence_gate.json
textcraft/data/recipes/acacia_planks.json
textcraft/data/recipes/acacia_pressure_plate.json
textcraft/data/recipes/acacia_sign.json
textcraft/data/recipes/acacia_slab.json
textcraft/data/recipes/acacia_stairs.json
textcraft/data/recipes/acacia_trapdoor.json
textcraft/data/recipes/acacia_wood.json
textcraft/data/recipes/activator_rail.json
textcraft/data/recipes/andesite.json
textcraft/data/recipes/andesite_slab.json
textcraft/data/recipes/andesite_slab_from_andesite_stonecutting.json
textcraft/data/recipes/andesite_stairs.json
textcraft/data/recipes/andesite_stairs_from_andesite_stonecutting.json
textcraft/data/recipes/andesite_wall.json
textcraft/data/recipes/andesite_wall_from_andesite_stonecutting.json
textcraft/data/recipes/anvil.json
textcraft/data/recipes/armor_dye.json
textcraft/data/recipes/armor_stand.json
textcraft/data/recipes/arrow.json
textcraft/data/recipes/baked_potato.json
textcraft/data/recipes/baked_potato_from_campfire_cooking.json
textcraft/data/recipes/baked_potato_from_smoking.json
textcraft/data/recipes/banner_duplicate.json
textcraft/data/recipes/barrel.json
textcraft/data/recipes/beacon.json
textcraft/data/recipes/beehive.json
textcraft/data/recipes/beetroot_soup.json
textcraft/data/recipes/birch_boat.json
textcraft/data/recipes/birch_button.json
textcraft/data/recipes/birch_door.json
textcraft/data/recipes/birch_fence.json
textcraft/data/recipes/birch_fence_gate.json
textcraft/data/recipes/birch_planks.json
textcraft/data/recipes/birch_pressure_plate.json
textcraft/data/recipes/birch_sign.json
textcraft/data/recipes/birch_slab.json
textcraft/data/recipes/birch_stairs.json
textcraft/data/recipes/birch_trapdoor.json
textcraft-0.0.2.dist-info/METADATA
textcraft-0.0.2.dist-info/WHEEL
textcraft-0.0.2.dist-info/top_level.txt
textcraft-0.0.2.dist-info/RECORD
