Metadata-Version: 2.2
Name: textcraft
Version: 0.0.2
Summary: Textcraft environment
Author-email: Nikolai Rozanov <nikolai.rozanov@gmail.com>
Requires-Dist: gymnasium>=0.26.0
Requires-Dist: numpy>=1.24.0
